upcast/__init__.py
upcast/__main__.py
upcast/main.py
upcast/common/__init__.py
upcast/common/ast_utils.py
upcast/common/cli.py
upcast/common/code_utils.py
upcast/common/export.py
upcast/common/file_utils.py
upcast/common/patterns.py
upcast/common/scanner_base.py
upcast/common/django/__init__.py
upcast/common/django/model_parser.py
upcast/common/django/model_utils.py
upcast/common/django/router_parser.py
upcast/common/django/settings_parser.py
upcast/common/django/settings_utils.py
upcast/common/django/url_parser.py
upcast/common/django/view_resolver.py
upcast/common/signals/__init__.py
upcast/common/signals/signal_checker.py
upcast/common/signals/signal_parser.py
upcast/models/__init__.py
upcast/models/base.py
upcast/models/blocking_operations.py
upcast/models/complexity.py
upcast/models/concurrency.py
upcast/models/django_models.py
upcast/models/django_settings.py
upcast/models/django_urls.py
upcast/models/env_vars.py
upcast/models/exceptions.py
upcast/models/http_requests.py
upcast/models/logging.py
upcast/models/metrics.py
upcast/models/module_symbols.py
upcast/models/redis_usage.py
upcast/models/signals.py
upcast/models/unit_tests.py
upcast/scanners/__init__.py
upcast/scanners/blocking_operations.py
upcast/scanners/complexity.py
upcast/scanners/concurrency.py
upcast/scanners/django_models.py
upcast/scanners/django_settings.py
upcast/scanners/django_urls.py
upcast/scanners/env_vars.py
upcast/scanners/exceptions.py
upcast/scanners/http_requests.py
upcast/scanners/logging_scanner.py
upcast/scanners/metrics.py
upcast/scanners/module_symbols.py
upcast/scanners/redis_usage.py
upcast/scanners/signals.py
upcast/scanners/unit_tests.py
upcast-1.1.0.dist-info/METADATA
upcast-1.1.0.dist-info/WHEEL
upcast-1.1.0.dist-info/entry_points.txt
upcast-1.1.0.dist-info/licenses/LICENSE
upcast-1.1.0.dist-info/RECORD
