Metadata-Version: 2.4
Name: upcast
Version: 1.1.0
Summary: AST tools
Project-URL: Repository, https://github.com/mrlyc/upcast
Project-URL: Documentation, https://mrlyc.github.io/upcast/
Author-email: MrLYC <github@m.mrlyc.com>
License: MIT License
License-File: LICENSE
Requires-Python: <4.0,>=3.9
Requires-Dist: astroid>=3.0.0
Requires-Dist: click>=8.1.7
Requires-Dist: pydantic>=2.9.2
Requires-Dist: pyyaml>=6.0.0
Provides-Extra: dev
Requires-Dist: black>=24.10.0; extra == 'dev'
Requires-Dist: flake8>=7.1.1; extra == 'dev'
Requires-Dist: ipdb>=0.13.13; extra == 'dev'
Requires-Dist: mypy>=1.5.1; extra == 'dev'
Requires-Dist: pre-commit>=3.4.0; extra == 'dev'
Requires-Dist: pytest-cov>=4.0.0; extra == 'dev'
Requires-Dist: pytest>=7.2.0; extra == 'dev'
Requires-Dist: ruff>=0.7.3; extra == 'dev'
Requires-Dist: tox>=4.11.1; extra == 'dev'
